LICENSE.md
MANIFEST.in
README.rst
pyproject.toml
requirements.core.txt
requirements.txt
setup.py
core_file_preview_app/__init__.py
core_file_preview_app/urls.py
core_file_preview_app.egg-info/PKG-INFO
core_file_preview_app.egg-info/SOURCES.txt
core_file_preview_app.egg-info/dependency_links.txt
core_file_preview_app.egg-info/requires.txt
core_file_preview_app.egg-info/top_level.txt
core_file_preview_app/static/core_file_preview_app/user/css/file_preview.css
core_file_preview_app/static/core_file_preview_app/user/js/file_preview.js
core_file_preview_app/static/core_file_preview_app/user/js/file_preview.raw.js
core_file_preview_app/templates/core_file_preview_app/user/file_preview_modal.html
core_file_preview_app/views/__init__.py
core_file_preview_app/views/user/__init__.py
core_file_preview_app/views/user/ajax.py
tests/__init__.py
tests/test_settings.py