Metadata-Version: 2.1
Name: core-file-preview-app
Version: 2.19.0
Summary: File preview functionalities for the curator core project
Home-page: https://github.com/usnistgov/core_main_app
Author: NIST IT Lab
Author-email: itl_inquiries@nist.gov
License-File: LICENSE.md
